{"event":"2024","members":{"2847684":{"stars":0,"id":2847684,"completion_day_level":{},"last_star_ts":0,"local_score":0,"name":"ColinBroughNHS","global_score":0},"3215757":{"last_star_ts":0,"name":"Michael Cheng","local_score":0,"global_score":0,"id":3215757,"completion_day_level":{},"stars":0},"2283942":{"global_score":0,"local_score":0,"name":"Mark Charlton","last_star_ts":0,"stars":0,"completion_day_level":{},"id":2283942},"214666":{"global_score":0,"local_score":525,"name":null,"last_star_ts":1734279158,"stars":4,"completion_day_level":{"1":{"2":{"get_star_ts":1734195880,"star_index":2558897},"1":{"get_star_ts":1734192691,"star_index":2554290}},"2":{"1":{"get_star_ts":1734226972,"star_index":2594392},"2":{"get_star_ts":1734279158,"star_index":2657445}}},"id":214666},"1691297":{"id":1691297,"completion_day_level":{},"stars":0,"last_star_ts":0,"name":"dspools","local_score":0,"global_score":0},"3239668":{"local_score":5430,"name":"r-cemper","global_score":0,"last_star_ts":1734500052,"completion_day_level":{"3":{"1":{"get_star_ts":1733256602,"star_index":749529},"2":{"get_star_ts":1733256632,"star_index":749626}},"1":{"2":{"star_index":739874,"get_star_ts":1733253881},"1":{"star_index":739735,"get_star_ts":1733253844}},"18":{"2":{"star_index":2887970,"get_star_ts":1734500052},"1":{"star_index":2887897,"get_star_ts":1734500028}},"17":{"2":{"get_star_ts":1734419327,"star_index":2805488},"1":{"get_star_ts":1734415339,"star_index":2800277}},"2":{"1":{"star_index":746406,"get_star_ts":1733255701},"2":{"get_star_ts":1733255717,"star_index":746463}},"6":{"2":{"get_star_ts":1733477822,"star_index":1320962},"1":{"star_index":1320918,"get_star_ts":1733477805}},"4":{"2":{"get_star_ts":1733319754,"star_index":925418},"1":{"get_star_ts":1733319734,"star_index":925346}},"10":{"1":{"get_star_ts":1733809105,"star_index":1968206},"2":{"get_star_ts":1733809121,"star_index":1968275}},"7":{"2":{"star_index":1481231,"get_star_ts":1733555197},"1":{"star_index":1481190,"get_star_ts":1733555177}},"14":{"1":{"get_star_ts":1734157184,"star_index":2500016},"2":{"star_index":2501792,"get_star_ts":1734158175}},"15":{"2":{"star_index":2610541,"get_star_ts":1734244317},"1":{"star_index":2610257,"get_star_ts":1734244124}},"11":{"2":{"get_star_ts":1733898233,"star_index":2129362},"1":{"get_star_ts":1733898214,"star_index":2129313}},"8":{"1":{"star_index":1651950,"get_star_ts":1733641051},"2":{"get_star_ts":1733641071,"star_index":1651985}},"5":{"1":{"get_star_ts":1733384775,"star_index":1095345},"2":{"get_star_ts":1733384795,"star_index":1095403}},"16":{"1":{"get_star_ts":1734329374,"star_index":2710550},"2":{"star_index":2710575,"get_star_ts":1734329394}},"12":{"2":{"star_index":2263845,"get_star_ts":1733982730},"1":{"star_index":2263750,"get_star_ts":1733982697}},"9":{"2":{"star_index":1806612,"get_star_ts":1733723386},"1":{"star_index":1806530,"get_star_ts":1733723365}},"13":{"2":{"get_star_ts":1734067678,"star_index":2375649},"1":{"get_star_ts":1734067658,"star_index":2375573}}},"id":3239668,"stars":36},"208231":{"stars":0,"id":208231,"completion_day_level":{},"last_star_ts":0,"name":"Daniel Reck","local_score":0,"global_score":0},"1549179":{"stars":0,"completion_day_level":{},"id":1549179,"local_score":0,"name":"Benjamin Spead","global_score":0,"last_star_ts":0},"557268":{"global_score":0,"local_score":0,"name":"Aric West","last_star_ts":0,"completion_day_level":{},"id":557268,"stars":0},"186041":{"id":186041,"completion_day_level":{},"stars":0,"last_star_ts":0,"global_score":0,"local_score":0,"name":"Sean Connelly"},"458972":{"id":458972,"completion_day_level":{},"stars":0,"last_star_ts":0,"name":"Sergei Shutov","local_score":0,"global_score":0},"1114807":{"completion_day_level":{},"id":1114807,"stars":0,"global_score":0,"local_score":0,"name":"ya5awa5","last_star_ts":0},"616144":{"local_score":0,"name":"akshatpv","global_score":0,"last_star_ts":0,"stars":0,"completion_day_level":{},"id":616144},"3251201":{"last_star_ts":1733148793,"local_score":427,"global_score":0,"name":"Gary Nguyen","stars":3,"id":3251201,"completion_day_level":{"2":{"1":{"get_star_ts":1733148793,"star_index":364230}},"1":{"2":{"get_star_ts":1733147746,"star_index":360037},"1":{"get_star_ts":1733147519,"star_index":359091}}}},"972753":{"stars":0,"completion_day_level":{},"id":972753,"local_score":0,"global_score":0,"name":"rcemper","last_star_ts":0},"479157":{"id":479157,"completion_day_level":{},"stars":0,"last_star_ts":0,"local_score":0,"name":"Fernando Viana Maia","global_score":0},"247591":{"stars":0,"id":247591,"completion_day_level":{},"last_star_ts":0,"local_score":0,"global_score":0,"name":"Stephen Wilson"},"2914707":{"name":"gbertolottiKS","local_score":0,"global_score":0,"last_star_ts":0,"completion_day_level":{},"id":2914707,"stars":0},"782124":{"local_score":0,"global_score":0,"name":"Udo Leimberger","last_star_ts":0,"completion_day_level":{},"id":782124,"stars":0},"4430343":{"stars":0,"completion_day_level":{},"id":4430343,"local_score":0,"name":"Newe","global_score":0,"last_star_ts":0},"1067218":{"last_star_ts":0,"name":"gvatash","local_score":0,"global_score":0,"id":1067218,"completion_day_level":{},"stars":0},"3835789":{"local_score":0,"name":"Dang Quang Vi","global_score":0,"last_star_ts":0,"completion_day_level":{},"id":3835789,"stars":0},"3406019":{"stars":0,"id":3406019,"completion_day_level":{},"last_star_ts":0,"local_score":0,"global_score":0,"name":"iscChris"},"663576":{"stars":0,"id":663576,"completion_day_level":{},"last_star_ts":0,"name":"rcemper","local_score":0,"global_score":0},"1849688":{"completion_day_level":{},"id":1849688,"stars":0,"local_score":0,"name":"maxisimo","global_score":0,"last_star_ts":0},"717816":{"name":"CrashAvery","local_score":0,"global_score":0,"last_star_ts":0,"stars":0,"completion_day_level":{},"id":717816},"977602":{"id":977602,"completion_day_level":{},"stars":0,"last_star_ts":0,"local_score":0,"global_score":0,"name":"Steven Potashnyk"},"3860190":{"local_score":0,"global_score":0,"name":null,"last_star_ts":0,"stars":0,"completion_day_level":{},"id":3860190},"269798":{"last_star_ts":0,"global_score":0,"local_score":0,"name":"Keith Avery","stars":0,"id":269798,"completion_day_level":{}},"861457":{"last_star_ts":0,"local_score":0,"global_score":0,"name":"Thomas Bagh","stars":0,"id":861457,"completion_day_level":{}},"2907798":{"stars":0,"completion_day_level":{},"id":2907798,"local_score":0,"global_score":0,"name":"abracchettiKS","last_star_ts":0},"2792798":{"last_star_ts":0,"name":"Shafran Cat","local_score":0,"global_score":0,"stars":0,"id":2792798,"completion_day_level":{}},"3507935":{"name":"Noah Dohrmann","local_score":1083,"global_score":0,"last_star_ts":1733797859,"stars":8,"completion_day_level":{"2":{"2":{"star_index":1622572,"get_star_ts":1733624520},"1":{"star_index":1614439,"get_star_ts":1733616004}},"4":{"2":{"get_star_ts":1733797859,"star_index":1950033},"1":{"star_index":1792940,"get_star_ts":1733714687}},"3":{"2":{"get_star_ts":1733704307,"star_index":1784817},"1":{"star_index":1776585,"get_star_ts":1733697602}},"1":{"2":{"get_star_ts":1733535042,"star_index":1445582},"1":{"star_index":804559,"get_star_ts":1733281786}}},"id":3507935},"2668789":{"last_star_ts":0,"local_score":0,"name":"Petchanop","global_score":0,"id":2668789,"completion_day_level":{},"stars":0},"523858":{"name":"Len Goodkin","local_score":0,"global_score":0,"last_star_ts":0,"completion_day_level":{},"id":523858,"stars":0},"3263475":{"local_score":0,"name":"hsullivaisc","global_score":0,"last_star_ts":0,"stars":0,"completion_day_level":{},"id":3263475},"2793794":{"global_score":0,"local_score":0,"name":"John Mesin","last_star_ts":0,"completion_day_level":{},"id":2793794,"stars":0},"4686354":{"local_score":0,"global_score":0,"name":"20songe","last_star_ts":0,"stars":0,"completion_day_level":{},"id":4686354},"1014892":{"name":"Kurro López","local_score":0,"global_score":0,"last_star_ts":0,"completion_day_level":{},"id":1014892,"stars":0},"2413574":{"last_star_ts":0,"name":"Muhammad Umar Waseem","local_score":0,"global_score":0,"stars":0,"id":2413574,"completion_day_level":{}},"2947516":{"last_star_ts":0,"name":"Robert Cemper","local_score":0,"global_score":0,"id":2947516,"completion_day_level":{},"stars":0},"753492":{"id":753492,"completion_day_level":{},"stars":0,"last_star_ts":0,"name":"Lucas bourré","local_score":0,"global_score":0},"3740788":{"stars":18,"id":3740788,"completion_day_level":{"5":{"1":{"get_star_ts":1733409744,"star_index":1166937},"2":{"get_star_ts":1733414876,"star_index":1181317}},"6":{"2":{"star_index":1419347,"get_star_ts":1733518657},"1":{"star_index":1377002,"get_star_ts":1733500017}},"7":{"1":{"star_index":1594641,"get_star_ts":1733604552},"2":{"star_index":1594777,"get_star_ts":1733604617}},"4":{"1":{"get_star_ts":1733341391,"star_index":991809},"2":{"star_index":994992,"get_star_ts":1733342397}},"9":{"1":{"star_index":1921514,"get_star_ts":1733777197},"2":{"get_star_ts":1733777214,"star_index":1921555}},"2":{"2":{"get_star_ts":1733173878,"star_index":466754},"1":{"star_index":462348,"get_star_ts":1733172787}},"1":{"1":{"star_index":455189,"get_star_ts":1733171018},"2":{"star_index":471518,"get_star_ts":1733175074}},"3":{"1":{"star_index":671002,"get_star_ts":1733234761},"2":{"star_index":673177,"get_star_ts":1733235372}},"8":{"2":{"star_index":1758293,"get_star_ts":1733688559},"1":{"star_index":1756327,"get_star_ts":1733687628}}},"last_star_ts":1733777214,"local_score":2598,"global_score":0,"name":"Peter Zubiago"},"306904":{"completion_day_level":{},"id":306904,"stars":0,"name":"David Crawford","local_score":0,"global_score":0,"last_star_ts":0},"3935390":{"local_score":0,"name":"SubstantialProduct27","global_score":0,"last_star_ts":0,"stars":0,"completion_day_level":{},"id":3935390},"64734":{"local_score":0,"name":"Eduard","global_score":0,"last_star_ts":0,"completion_day_level":{},"id":64734,"stars":0},"1128565":{"completion_day_level":{"3":{"2":{"get_star_ts":1733202551,"star_index":527285},"1":{"get_star_ts":1733202338,"star_index":524595}},"1":{"2":{"get_star_ts":1733029534,"star_index":1657},"1":{"get_star_ts":1733029429,"star_index":0}},"2":{"1":{"star_index":223240,"get_star_ts":1733116266},"2":{"get_star_ts":1733116795,"star_index":228970}},"6":{"2":{"star_index":1344686,"get_star_ts":1733487347},"1":{"get_star_ts":1733485353,"star_index":1340079}},"10":{"2":{"star_index":2029579,"get_star_ts":1733837816},"1":{"star_index":2028955,"get_star_ts":1733837468}},"7":{"1":{"get_star_ts":1733573128,"star_index":1523745},"2":{"star_index":1526807,"get_star_ts":1733574459}},"4":{"2":{"star_index":868489,"get_star_ts":1733301851},"1":{"star_index":866909,"get_star_ts":1733301421}},"18":{"1":{"star_index":2887895,"get_star_ts":1734500028}},"17":{"2":{"get_star_ts":1734437470,"star_index":2825973},"1":{"get_star_ts":1734434359,"star_index":2822811}},"15":{"1":{"get_star_ts":1734313913,"star_index":2697146}},"11":{"1":{"star_index":2110066,"get_star_ts":1733893462},"2":{"star_index":2115778,"get_star_ts":1733894243}},"8":{"2":{"get_star_ts":1733661664,"star_index":1698613},"1":{"star_index":1692953,"get_star_ts":1733659260}},"14":{"1":{"star_index":2548063,"get_star_ts":1734188699},"2":{"get_star_ts":1734199673,"star_index":2564122}},"12":{"1":{"get_star_ts":1734008391,"star_index":2303993},"2":{"get_star_ts":1734019648,"star_index":2321111}},"9":{"1":{"star_index":1848916,"get_star_ts":1733742369},"2":{"star_index":1863226,"get_star_ts":1733749642}},"13":{"1":{"get_star_ts":1734066798,"star_index":2372507},"2":{"get_star_ts":1734067342,"star_index":2374419}},"5":{"2":{"star_index":1131262,"get_star_ts":1733396280},"1":{"get_star_ts":1733396147,"star_index":1130883}}},"id":1128565,"stars":32,"local_score":4827,"name":"maxymczech","global_score":0,"last_star_ts":1734500028},"1725279":{"id":1725279,"completion_day_level":{},"stars":0,"last_star_ts":0,"local_score":0,"global_score":0,"name":"jackpto"},"2934245":{"stars":0,"id":2934245,"completion_day_level":{},"last_star_ts":0,"name":"Evgeny Shvarov","local_score":0,"global_score":0},"1738359":{"stars":0,"completion_day_level":{},"id":1738359,"local_score":0,"global_score":0,"name":"José Roberto Pereira Junior","last_star_ts":0},"4306651":{"global_score":0,"local_score":4575,"name":"JFerreB","last_star_ts":1734346434,"completion_day_level":{"9":{"2":{"get_star_ts":1733773654,"star_index":1913770},"1":{"star_index":1912733,"get_star_ts":1733773149}},"13":{"2":{"star_index":2459494,"get_star_ts":1734119553},"1":{"star_index":2459235,"get_star_ts":1734119333}},"12":{"1":{"star_index":2340122,"get_star_ts":1734033004},"2":{"star_index":2351709,"get_star_ts":1734040387}},"5":{"2":{"get_star_ts":1733433028,"star_index":1229629},"1":{"get_star_ts":1733426766,"star_index":1212252}},"16":{"1":{"get_star_ts":1734346434,"star_index":2730385}},"8":{"1":{"get_star_ts":1733641119,"star_index":1652070},"2":{"get_star_ts":1733642200,"star_index":1654060}},"11":{"2":{"get_star_ts":1733956317,"star_index":2237933},"1":{"get_star_ts":1733956211,"star_index":2237789}},"15":{"1":{"get_star_ts":1734254460,"star_index":2622486},"2":{"get_star_ts":1734261078,"star_index":2631756}},"14":{"1":{"star_index":2573964,"get_star_ts":1734207251},"2":{"get_star_ts":1734211730,"star_index":2579866}},"4":{"1":{"star_index":1016559,"get_star_ts":1733349221},"2":{"star_index":1019485,"get_star_ts":1733350214}},"7":{"1":{"get_star_ts":1733555555,"star_index":1481955},"2":{"get_star_ts":1733555977,"star_index":1482792}},"10":{"2":{"get_star_ts":1733865576,"star_index":2081808},"1":{"get_star_ts":1733865453,"star_index":2081576}},"6":{"1":{"get_star_ts":1733476669,"star_index":1317784},"2":{"star_index":1323795,"get_star_ts":1733478862}},"2":{"1":{"get_star_ts":1733164591,"star_index":429151},"2":{"get_star_ts":1733167374,"star_index":440227}},"1":{"2":{"star_index":41023,"get_star_ts":1733043320},"1":{"star_index":38616,"get_star_ts":1733042459}},"3":{"2":{"star_index":762916,"get_star_ts":1733260375},"1":{"get_star_ts":1733254190,"star_index":740998}}},"id":4306651,"stars":31},"907445":{"last_star_ts":1734427155,"local_score":5135,"global_score":0,"name":"Jarjar 314","stars":34,"id":907445,"completion_day_level":{"12":{"1":{"get_star_ts":1733990872,"star_index":2278226},"2":{"star_index":2289405,"get_star_ts":1733998027}},"13":{"1":{"star_index":2387952,"get_star_ts":1734073000},"2":{"star_index":2400750,"get_star_ts":1734080677}},"9":{"1":{"get_star_ts":1733739073,"star_index":1841873},"2":{"star_index":1846024,"get_star_ts":1733740978}},"16":{"2":{"get_star_ts":1734347472,"star_index":2731522},"1":{"star_index":2729670,"get_star_ts":1734345783}},"5":{"2":{"star_index":1108230,"get_star_ts":1733388784},"1":{"star_index":1087192,"get_star_ts":1733382099}},"15":{"2":{"star_index":2684480,"get_star_ts":1734298939},"1":{"get_star_ts":1734294881,"star_index":2678866}},"11":{"1":{"get_star_ts":1733900343,"star_index":2133965},"2":{"star_index":2134032,"get_star_ts":1733900380}},"8":{"1":{"star_index":1655833,"get_star_ts":1733643188},"2":{"get_star_ts":1733643500,"star_index":1656396}},"14":{"2":{"star_index":2510834,"get_star_ts":1734164730},"1":{"get_star_ts":1734163102,"star_index":2508595}},"2":{"1":{"star_index":273716,"get_star_ts":1733126749},"2":{"get_star_ts":1733127030,"star_index":274858}},"7":{"2":{"star_index":1485364,"get_star_ts":1733557262},"1":{"get_star_ts":1733556148,"star_index":1483135}},"10":{"1":{"get_star_ts":1733814770,"star_index":1983006},"2":{"get_star_ts":1733814888,"star_index":1983265}},"4":{"2":{"star_index":846585,"get_star_ts":1733295532},"1":{"star_index":845683,"get_star_ts":1733295251}},"6":{"2":{"get_star_ts":1733468080,"star_index":1295093},"1":{"get_star_ts":1733467475,"star_index":1293473}},"17":{"1":{"get_star_ts":1734422981,"star_index":2809743},"2":{"get_star_ts":1734427155,"star_index":2814474}},"3":{"2":{"get_star_ts":1733212382,"star_index":581802},"1":{"star_index":565785,"get_star_ts":1733208784}},"1":{"1":{"get_star_ts":1733038025,"star_index":28208},"2":{"star_index":28544,"get_star_ts":1733038189}}}},"1568871":{"last_star_ts":0,"name":"Sergei Shutov (Banksia Global)","local_score":0,"global_score":0,"stars":0,"id":1568871,"completion_day_level":{}},"969186":{"id":969186,"completion_day_level":{},"stars":0,"last_star_ts":0,"local_score":0,"name":"Alexander Koblov","global_score":0},"1810568":{"id":1810568,"completion_day_level":{},"stars":0,"last_star_ts":0,"local_score":0,"global_score":0,"name":"NjekTt"},"3247832":{"id":3247832,"completion_day_level":{},"stars":0,"last_star_ts":0,"local_score":0,"global_score":0,"name":"DanielAguilarGarcia"},"1209513":{"completion_day_level":{},"id":1209513,"stars":0,"local_score":0,"global_score":0,"name":"Ggimp","last_star_ts":0},"4836970":{"completion_day_level":{},"id":4836970,"stars":0,"local_score":0,"name":"fanji-isc","global_score":0,"last_star_ts":0},"1589062":{"completion_day_level":{},"id":1589062,"stars":0,"global_score":0,"local_score":0,"name":"ISC Jacques HUSER","last_star_ts":0},"280091":{"stars":17,"completion_day_level":{"3":{"2":{"star_index":567948,"get_star_ts":1733209283},"1":{"get_star_ts":1733206772,"star_index":557020}},"1":{"1":{"star_index":121289,"get_star_ts":1733070572},"2":{"get_star_ts":1733070912,"star_index":122260}},"8":{"2":{"star_index":1702302,"get_star_ts":1733663292},"1":{"star_index":1689000,"get_star_ts":1733657623}},"5":{"1":{"get_star_ts":1733417349,"star_index":1188208},"2":{"get_star_ts":1733423688,"star_index":1204463}},"2":{"1":{"get_star_ts":1733122156,"star_index":255362},"2":{"get_star_ts":1733125542,"star_index":268732}},"6":{"1":{"get_star_ts":1733468748,"star_index":1296730},"2":{"star_index":1305732,"get_star_ts":1733472244}},"9":{"1":{"get_star_ts":1733780435,"star_index":1928603}},"7":{"1":{"star_index":1553202,"get_star_ts":1733585342},"2":{"star_index":1562657,"get_star_ts":1733589313}},"4":{"1":{"get_star_ts":1733292814,"star_index":836733},"2":{"star_index":839222,"get_star_ts":1733293439}}},"id":280091,"local_score":2537,"name":"Oskari Kosonen","global_score":0,"last_star_ts":1733780435},"1533783":{"id":1533783,"completion_day_level":{},"stars":0,"last_star_ts":0,"name":"banusri99","local_score":0,"global_score":0},"865349":{"stars":0,"completion_day_level":{},"id":865349,"local_score":0,"name":"OlgaZavrazhnova","global_score":0,"last_star_ts":0},"2425070":{"stars":0,"completion_day_level":{},"id":2425070,"name":"hazamashoken","local_score":0,"global_score":0,"last_star_ts":0},"2608604":{"last_star_ts":1734337730,"name":"Chhayank Warad","local_score":1902,"global_score":0,"id":2608604,"completion_day_level":{"5":{"1":{"get_star_ts":1733426891,"star_index":1212594}},"6":{"1":{"star_index":1708577,"get_star_ts":1733666207}},"7":{"1":{"star_index":1926035,"get_star_ts":1733779238}},"4":{"2":{"star_index":1155271,"get_star_ts":1733405483},"1":{"star_index":1152797,"get_star_ts":1733404584}},"2":{"1":{"get_star_ts":1733117280,"star_index":233036},"2":{"star_index":253313,"get_star_ts":1733121610}},"1":{"1":{"get_star_ts":1733048308,"star_index":56108},"2":{"get_star_ts":1733048476,"star_index":56606}},"3":{"2":{"star_index":558265,"get_star_ts":1733207040},"1":{"star_index":546785,"get_star_ts":1733204731}},"8":{"1":{"get_star_ts":1733820958,"star_index":1996861}},"11":{"1":{"star_index":2720437,"get_star_ts":1734337730}}},"stars":13},"3416557":{"completion_day_level":{},"id":3416557,"stars":0,"global_score":0,"local_score":0,"name":"isc-bquirk","last_star_ts":0},"476331":{"id":476331,"completion_day_level":{},"stars":0,"last_star_ts":0,"global_score":0,"local_score":0,"name":"Jack"},"2438880":{"id":2438880,"completion_day_level":{},"stars":0,"last_star_ts":0,"local_score":0,"global_score":0,"name":"davi massaru"},"1165922":{"global_score":0,"local_score":0,"name":"Irina Podmazko","last_star_ts":0,"stars":0,"completion_day_level":{},"id":1165922},"495499":{"local_score":1928,"name":"Jani Hurskainen","global_score":0,"last_star_ts":1734072101,"completion_day_level":{"3":{"2":{"star_index":566359,"get_star_ts":1733208925},"1":{"star_index":558076,"get_star_ts":1733206999}},"5":{"1":{"star_index":1103701,"get_star_ts":1733387401},"2":{"star_index":1359649,"get_star_ts":1733493455}},"1":{"2":{"get_star_ts":1733038767,"star_index":29736},"1":{"star_index":28730,"get_star_ts":1733038279}},"2":{"1":{"star_index":250396,"get_star_ts":1733120850},"2":{"star_index":258798,"get_star_ts":1733123075}},"6":{"2":{"get_star_ts":1733812916,"star_index":1979037},"1":{"star_index":1884687,"get_star_ts":1733759725}},"4":{"1":{"get_star_ts":1733298851,"star_index":857848},"2":{"star_index":865542,"get_star_ts":1733301004}},"7":{"1":{"star_index":2386362,"get_star_ts":1734072101}}},"id":495499,"stars":13},"167530":{"completion_day_level":{},"id":167530,"stars":0,"global_score":0,"local_score":0,"name":"Dieter PAUL","last_star_ts":0},"1531360":{"last_star_ts":0,"local_score":0,"global_score":0,"name":"Pulkit Girdhar","stars":0,"id":1531360,"completion_day_level":{}},"3535310":{"last_star_ts":1734500170,"name":"k-otto-r","local_score":5397,"global_score":0,"id":3535310,"completion_day_level":{"1":{"2":{"star_index":741440,"get_star_ts":1733254310},"1":{"get_star_ts":1733254288,"star_index":741353}},"3":{"1":{"get_star_ts":1733256717,"star_index":749927},"2":{"star_index":749964,"get_star_ts":1733256731}},"6":{"2":{"get_star_ts":1733477942,"star_index":1321265},"1":{"get_star_ts":1733477924,"star_index":1321217}},"10":{"1":{"get_star_ts":1733809181,"star_index":1968557},"2":{"get_star_ts":1733809199,"star_index":1968639}},"4":{"1":{"star_index":925815,"get_star_ts":1733319883},"2":{"get_star_ts":1733319893,"star_index":925840}},"7":{"1":{"get_star_ts":1733555278,"star_index":1481389},"2":{"star_index":1481418,"get_star_ts":1733555292}},"2":{"1":{"star_index":747241,"get_star_ts":1733255947},"2":{"star_index":747299,"get_star_ts":1733255962}},"18":{"1":{"get_star_ts":1734500153,"star_index":2888277},"2":{"get_star_ts":1734500170,"star_index":2888339}},"17":{"2":{"star_index":2805398,"get_star_ts":1734419240},"1":{"get_star_ts":1734415441,"star_index":2800412}},"8":{"1":{"get_star_ts":1733641207,"star_index":1652214},"2":{"star_index":1652244,"get_star_ts":1733641221}},"15":{"2":{"get_star_ts":1734244503,"star_index":2610790},"1":{"star_index":2610715,"get_star_ts":1734244449}},"11":{"1":{"star_index":2129718,"get_star_ts":1733898381},"2":{"star_index":2131181,"get_star_ts":1733899035}},"14":{"1":{"get_star_ts":1734157267,"star_index":2500181},"2":{"star_index":2500461,"get_star_ts":1734157408}},"13":{"2":{"star_index":2376071,"get_star_ts":1734067803},"1":{"star_index":2376006,"get_star_ts":1734067784}},"9":{"1":{"star_index":1807406,"get_star_ts":1733723638},"2":{"get_star_ts":1733723671,"star_index":1807526}},"12":{"1":{"star_index":2264281,"get_star_ts":1733982904},"2":{"get_star_ts":1733982927,"star_index":2264334}},"5":{"1":{"get_star_ts":1733384860,"star_index":1095616},"2":{"star_index":1095689,"get_star_ts":1733384877}},"16":{"2":{"get_star_ts":1734329486,"star_index":2710705},"1":{"star_index":2710688,"get_star_ts":1734329471}}},"stars":36},"740763":{"stars":0,"completion_day_level":{},"id":740763,"local_score":0,"name":"Dmitrii Kuznetsov","global_score":0,"last_star_ts":0},"3301203":{"local_score":0,"name":"Rebecca Agustin","global_score":0,"last_star_ts":0,"stars":0,"completion_day_level":{},"id":3301203},"3921123":{"global_score":0,"local_score":0,"name":"Arturo Masero","last_star_ts":0,"stars":0,"completion_day_level":{},"id":3921123},"278596":{"completion_day_level":{},"id":278596,"stars":0,"global_score":0,"local_score":0,"name":"Robert Trifan","last_star_ts":0},"2869962":{"id":2869962,"completion_day_level":{},"stars":0,"last_star_ts":0,"local_score":0,"name":"uldlup","global_score":0},"1047595":{"id":1047595,"completion_day_level":{"2":{"1":{"get_star_ts":1733133891,"star_index":306403},"2":{"star_index":494127,"get_star_ts":1733182401}},"3":{"1":{"star_index":619126,"get_star_ts":1733220393},"2":{"get_star_ts":1733221813,"star_index":624979}},"1":{"2":{"get_star_ts":1733074083,"star_index":132114},"1":{"get_star_ts":1733073704,"star_index":131002}}},"stars":6,"last_star_ts":1733221813,"global_score":0,"local_score":875,"name":"rhodery"},"812240":{"last_star_ts":0,"global_score":0,"local_score":0,"name":"Kevin An","id":812240,"completion_day_level":{},"stars":0},"4576105":{"stars":0,"id":4576105,"completion_day_level":{},"last_star_ts":0,"name":"JouniValiaho-Mylab","local_score":0,"global_score":0},"1025096":{"local_score":0,"global_score":0,"name":"Kevin Majewski","last_star_ts":0,"completion_day_level":{},"id":1025096,"stars":0},"3246888":{"stars":0,"completion_day_level":{},"id":3246888,"global_score":0,"local_score":0,"name":"Raj Singh","last_star_ts":0},"688941":{"local_score":0,"global_score":0,"name":"jonasvandervennet","last_star_ts":0,"completion_day_level":{},"id":688941,"stars":0},"203331":{"stars":0,"completion_day_level":{},"id":203331,"local_score":0,"name":"Stuart Byrne","global_score":0,"last_star_ts":0},"3241073":{"local_score":0,"global_score":0,"name":"agaramudhala","last_star_ts":0,"completion_day_level":{},"id":3241073,"stars":0},"973649":{"name":"Dmitrii Kuznetsov","local_score":0,"global_score":0,"last_star_ts":0,"stars":0,"completion_day_level":{},"id":973649},"3310629":{"last_star_ts":0,"name":"Ajinkya Sonawane","local_score":0,"global_score":0,"id":3310629,"completion_day_level":{},"stars":0},"763831":{"stars":9,"id":763831,"completion_day_level":{"2":{"2":{"star_index":692931,"get_star_ts":1733240640},"1":{"star_index":458080,"get_star_ts":1733171737}},"4":{"1":{"get_star_ts":1733341975,"star_index":993623},"2":{"get_star_ts":1733347635,"star_index":1011699}},"3":{"2":{"get_star_ts":1733242809,"star_index":700996},"1":{"star_index":700323,"get_star_ts":1733242625}},"5":{"1":{"star_index":1182217,"get_star_ts":1733415197}},"1":{"2":{"get_star_ts":1733169816,"star_index":450197},"1":{"star_index":449212,"get_star_ts":1733169570}}},"last_star_ts":1733415197,"global_score":0,"local_score":1278,"name":"TylerFeldhege"},"974078":{"id":974078,"completion_day_level":{},"stars":0,"last_star_ts":0,"local_score":0,"global_score":0,"name":"AlexeyM64"},"4257799":{"completion_day_level":{},"id":4257799,"stars":0,"name":"Trogan-Kroll","local_score":0,"global_score":0,"last_star_ts":0},"2838043":{"local_score":0,"name":"k-otto-k","global_score":0,"last_star_ts":0,"completion_day_level":{},"id":2838043,"stars":0},"2443527":{"last_star_ts":0,"global_score":0,"local_score":0,"name":"unikrubii","stars":0,"id":2443527,"completion_day_level":{}},"185940":{"name":"Evgeny Shvarov","local_score":0,"global_score":0,"last_star_ts":0,"completion_day_level":{},"id":185940,"stars":0},"2382921":{"last_star_ts":0,"name":"Paul Cranston","local_score":0,"global_score":0,"id":2382921,"completion_day_level":{},"stars":0},"1246023":{"stars":0,"id":1246023,"completion_day_level":{},"last_star_ts":0,"global_score":0,"local_score":0,"name":"rcniinoi"},"3984008":{"stars":0,"id":3984008,"completion_day_level":{},"last_star_ts":0,"global_score":0,"local_score":0,"name":"Sundara Moorthy Jeganathan"},"2285598":{"completion_day_level":{"11":{"1":{"star_index":2478331,"get_star_ts":1734135078}},"1":{"1":{"get_star_ts":1733031603,"star_index":15040},"2":{"get_star_ts":1733032499,"star_index":17364}},"3":{"2":{"get_star_ts":1733269880,"star_index":788699},"1":{"get_star_ts":1733260590,"star_index":763712}},"6":{"1":{"star_index":1306565,"get_star_ts":1733472575}},"4":{"1":{"get_star_ts":1733324120,"star_index":938795},"2":{"star_index":974990,"get_star_ts":1733335785}},"7":{"1":{"get_star_ts":1733557554,"star_index":1485974},"2":{"get_star_ts":1733557970,"star_index":1486867}},"2":{"1":{"get_star_ts":1733170394,"star_index":452565},"2":{"get_star_ts":1733187026,"star_index":502297}},"5":{"2":{"star_index":1299797,"get_star_ts":1733469973},"1":{"star_index":1075570,"get_star_ts":1733378675}}},"id":2285598,"stars":14,"local_score":2052,"name":"Keith Avery","global_score":0,"last_star_ts":1734135078},"4125186":{"completion_day_level":{},"id":4125186,"stars":0,"local_score":0,"global_score":0,"name":"Patrick Pigna","last_star_ts":0},"539039":{"stars":34,"id":539039,"completion_day_level":{"3":{"2":{"star_index":2347051,"get_star_ts":1734037383},"1":{"get_star_ts":1734034314,"star_index":2342123}},"1":{"1":{"star_index":2337521,"get_star_ts":1734031184},"2":{"get_star_ts":1734031750,"star_index":2338320}},"2":{"2":{"get_star_ts":1734033619,"star_index":2341000},"1":{"star_index":2339516,"get_star_ts":1734032600}},"10":{"1":{"star_index":2543091,"get_star_ts":1734185455},"2":{"get_star_ts":1734186190,"star_index":2544242}},"7":{"1":{"star_index":2438127,"get_star_ts":1734104369},"2":{"star_index":2439852,"get_star_ts":1734105442}},"4":{"1":{"get_star_ts":1734038716,"star_index":2349095},"2":{"get_star_ts":1734040223,"star_index":2351483}},"6":{"2":{"get_star_ts":1734088728,"star_index":2413961},"1":{"get_star_ts":1734087735,"star_index":2412524}},"17":{"1":{"get_star_ts":1734420018,"star_index":2806271},"2":{"get_star_ts":1734455002,"star_index":2846437}},"15":{"2":{"get_star_ts":1734264358,"star_index":2636361},"1":{"star_index":2611622,"get_star_ts":1734245149}},"11":{"1":{"get_star_ts":1734188245,"star_index":2547347},"2":{"get_star_ts":1734193147,"star_index":2554975}},"8":{"1":{"star_index":2446375,"get_star_ts":1734109681},"2":{"get_star_ts":1734111287,"star_index":2448685}},"14":{"1":{"star_index":2569073,"get_star_ts":1734203488},"2":{"star_index":2570546,"get_star_ts":1734204619}},"12":{"2":{"star_index":2562883,"get_star_ts":1734198726},"1":{"get_star_ts":1734196389,"star_index":2559622}},"9":{"2":{"get_star_ts":1734183409,"star_index":2539977},"1":{"get_star_ts":1734161552,"star_index":2506465}},"13":{"2":{"star_index":2566437,"get_star_ts":1734201456},"1":{"star_index":2566157,"get_star_ts":1734201235}},"5":{"2":{"get_star_ts":1734043486,"star_index":2356005},"1":{"get_star_ts":1734041166,"star_index":2352798}},"16":{"2":{"star_index":2749122,"get_star_ts":1734362559},"1":{"get_star_ts":1734354735,"star_index":2739525}}},"last_star_ts":1734455002,"name":"Yuval Golan","local_score":4875,"global_score":0},"2291107":{"stars":35,"id":2291107,"completion_day_level":{"1":{"1":{"get_star_ts":1733031048,"star_index":13198},"2":{"get_star_ts":1733031227,"star_index":13831}},"3":{"2":{"get_star_ts":1733203529,"star_index":538178},"1":{"star_index":527504,"get_star_ts":1733202567}},"6":{"2":{"star_index":1286503,"get_star_ts":1733465045},"1":{"get_star_ts":1733462739,"star_index":1276575}},"10":{"2":{"star_index":1963370,"get_star_ts":1733808206},"1":{"get_star_ts":1733808091,"star_index":1962603}},"4":{"2":{"star_index":822787,"get_star_ts":1733290151},"1":{"get_star_ts":1733289868,"star_index":820775}},"7":{"2":{"get_star_ts":1733549417,"star_index":1464913},"1":{"get_star_ts":1733549188,"star_index":1463722}},"2":{"2":{"get_star_ts":1733116333,"star_index":224064},"1":{"star_index":221367,"get_star_ts":1733116117}},"18":{"1":{"star_index":2884909,"get_star_ts":1734499257}},"17":{"2":{"get_star_ts":1734419189,"star_index":2805341},"1":{"get_star_ts":1734416607,"star_index":2802102}},"8":{"1":{"get_star_ts":1733635305,"star_index":1634176},"2":{"star_index":1636291,"get_star_ts":1733635690}},"15":{"1":{"star_index":2617236,"get_star_ts":1734249939},"2":{"get_star_ts":1734256178,"star_index":2624802}},"11":{"1":{"get_star_ts":1733898693,"star_index":2130441},"2":{"star_index":2132432,"get_star_ts":1733899606}},"14":{"1":{"get_star_ts":1734154387,"star_index":2493085},"2":{"get_star_ts":1734156718,"star_index":2499147}},"9":{"2":{"get_star_ts":1733734107,"star_index":1830969},"1":{"star_index":1804089,"get_star_ts":1733722675}},"13":{"2":{"get_star_ts":1734071665,"star_index":2385522},"1":{"star_index":2379682,"get_star_ts":1734069000}},"12":{"1":{"get_star_ts":1733983213,"star_index":2265027},"2":{"get_star_ts":1733984924,"star_index":2268533}},"16":{"2":{"star_index":2711853,"get_star_ts":1734330306},"1":{"star_index":2710140,"get_star_ts":1734329082}},"5":{"1":{"get_star_ts":1733375969,"star_index":1060193},"2":{"get_star_ts":1733376973,"star_index":1067079}}},"last_star_ts":1734499257,"local_score":5392,"name":"Dominik Znidar","global_score":0},"3247172":{"last_star_ts":0,"local_score":0,"global_score":0,"name":"Arwa A.","stars":0,"id":3247172,"completion_day_level":{}},"1622907":{"id":1622907,"completion_day_level":{},"stars":0,"last_star_ts":0,"global_score":0,"local_score":0,"name":"strickers-git"},"2653896":{"id":2653896,"completion_day_level":{},"stars":0,"last_star_ts":0,"name":"Jaume Ferre","local_score":0,"global_score":0},"3704512":{"stars":0,"completion_day_level":{},"id":3704512,"local_score":0,"global_score":0,"name":"Dominique Dordain","last_star_ts":0},"19053":{"completion_day_level":{"6":{"1":{"get_star_ts":1733471327,"star_index":1303252}},"4":{"1":{"star_index":849299,"get_star_ts":1733296356},"2":{"get_star_ts":1733297254,"star_index":852344}},"9":{"1":{"get_star_ts":1733748525,"star_index":1860998}},"2":{"1":{"get_star_ts":1733126177,"star_index":271311},"2":{"get_star_ts":1733138840,"star_index":326471}},"5":{"1":{"star_index":1092493,"get_star_ts":1733383846}},"1":{"2":{"get_star_ts":1733060771,"star_index":93548},"1":{"star_index":93065,"get_star_ts":1733060591}},"3":{"2":{"star_index":643935,"get_star_ts":1733227119},"1":{"star_index":573138,"get_star_ts":1733210493}}},"id":19053,"stars":11,"global_score":0,"local_score":1639,"name":"Ivo ver eecke","last_star_ts":1733748525},"3691076":{"name":"Chris Marais","local_score":695,"global_score":0,"last_star_ts":1733769830,"completion_day_level":{"1":{"1":{"get_star_ts":1733072375,"star_index":126840},"2":{"star_index":180716,"get_star_ts":1733089485}},"3":{"1":{"star_index":1905870,"get_star_ts":1733769830}},"2":{"1":{"star_index":759263,"get_star_ts":1733259324},"2":{"star_index":1173843,"get_star_ts":1733412194}}},"id":3691076,"stars":5},"11389":{"stars":0,"completion_day_level":{},"id":11389,"name":"Bert Sarens","local_score":0,"global_score":0,"last_star_ts":0},"2382343":{"global_score":0,"local_score":0,"name":"heyding","last_star_ts":0,"completion_day_level":{},"id":2382343,"stars":0},"130669":{"stars":0,"id":130669,"completion_day_level":{},"last_star_ts":0,"global_score":0,"local_score":0,"name":"Dmitry Maslennikov"},"965699":{"local_score":0,"name":"Anastasia Dyubaylo","global_score":0,"last_star_ts":0,"stars":0,"completion_day_level":{},"id":965699},"858894":{"stars":0,"completion_day_level":{},"id":858894,"name":"Lucas","local_score":0,"global_score":0,"last_star_ts":0},"969435":{"name":"Vladimir Mologa","local_score":0,"global_score":0,"last_star_ts":0,"completion_day_level":{},"id":969435,"stars":0},"545857":{"local_score":0,"name":"Aidan Nagle","global_score":0,"last_star_ts":0,"stars":0,"completion_day_level":{},"id":545857},"513880":{"name":"Roger Taylor","local_score":0,"global_score":0,"last_star_ts":0,"completion_day_level":{},"id":513880,"stars":0},"741453":{"completion_day_level":{},"id":741453,"stars":0,"local_score":0,"name":"Mike","global_score":0,"last_star_ts":0},"1600930":{"local_score":0,"name":"Jesper Olsson","global_score":0,"last_star_ts":0,"stars":0,"completion_day_level":{},"id":1600930},"252146":{"local_score":0,"global_score":0,"name":"Steve Mik","last_star_ts":0,"completion_day_level":{},"id":252146,"stars":0},"1733907":{"stars":0,"id":1733907,"completion_day_level":{},"last_star_ts":0,"global_score":0,"local_score":0,"name":"alex2008alex"},"2342928":{"stars":0,"id":2342928,"completion_day_level":{},"last_star_ts":0,"local_score":0,"global_score":0,"name":"Laura Cavanaugh"},"673727":{"last_star_ts":1733323456,"global_score":0,"local_score":565,"name":"Oliver Wilms","stars":4,"id":673727,"completion_day_level":{"2":{"2":{"get_star_ts":1733323456,"star_index":936688},"1":{"star_index":374785,"get_star_ts":1733151351}},"1":{"1":{"get_star_ts":1733094604,"star_index":193218},"2":{"star_index":209333,"get_star_ts":1733106822}}}},"1069615":{"name":"goran7t","local_score":0,"global_score":0,"last_star_ts":0,"completion_day_level":{},"id":1069615,"stars":0},"2446389":{"name":"Paphawit Ngamchaliew","local_score":0,"global_score":0,"last_star_ts":0,"stars":0,"completion_day_level":{},"id":2446389},"2430000":{"global_score":0,"local_score":0,"name":"nwattana","last_star_ts":0,"completion_day_level":{},"id":2430000,"stars":0},"1303403":{"local_score":0,"global_score":0,"name":"Somebody In World","last_star_ts":0,"completion_day_level":{},"id":1303403,"stars":0},"3575160":{"local_score":0,"name":"Geoffrey Lu","global_score":0,"last_star_ts":0,"completion_day_level":{},"id":3575160,"stars":0},"411220":{"global_score":0,"local_score":5130,"name":"Joaquin Derrac Rus","last_star_ts":1734461401,"completion_day_level":{"17":{"2":{"get_star_ts":1734461401,"star_index":2853147},"1":{"get_star_ts":1734422181,"star_index":2808854}},"2":{"2":{"star_index":284299,"get_star_ts":1733129136},"1":{"get_star_ts":1733128655,"star_index":282150}},"4":{"2":{"get_star_ts":1733296799,"star_index":850800},"1":{"star_index":848264,"get_star_ts":1733296038}},"7":{"1":{"star_index":1486884,"get_star_ts":1733557977},"2":{"star_index":1488301,"get_star_ts":1733558637}},"10":{"1":{"get_star_ts":1733817274,"star_index":1988536},"2":{"get_star_ts":1733818883,"star_index":1992111}},"6":{"2":{"get_star_ts":1733472075,"star_index":1305296},"1":{"star_index":1303489,"get_star_ts":1733471416}},"3":{"1":{"star_index":577319,"get_star_ts":1733211433},"2":{"get_star_ts":1733211730,"star_index":578699}},"1":{"1":{"star_index":40922,"get_star_ts":1733043287},"2":{"star_index":41316,"get_star_ts":1733043417}},"5":{"1":{"star_index":1056711,"get_star_ts":1733375499},"2":{"star_index":1059105,"get_star_ts":1733375825}},"16":{"2":{"star_index":2720488,"get_star_ts":1734337778},"1":{"star_index":2719635,"get_star_ts":1734336992}},"12":{"1":{"get_star_ts":1733993816,"star_index":2282806},"2":{"star_index":2286539,"get_star_ts":1733996206}},"9":{"1":{"star_index":1839630,"get_star_ts":1733738070},"2":{"get_star_ts":1733742209,"star_index":1848604}},"13":{"1":{"get_star_ts":1734077082,"star_index":2394725},"2":{"get_star_ts":1734077216,"star_index":2394922}},"14":{"1":{"get_star_ts":1734171619,"star_index":2521335},"2":{"get_star_ts":1734173427,"star_index":2524332}},"15":{"2":{"star_index":2632859,"get_star_ts":1734261855},"1":{"star_index":2628640,"get_star_ts":1734258980}},"11":{"2":{"star_index":2141531,"get_star_ts":1733903780},"1":{"star_index":2141006,"get_star_ts":1733903550}},"8":{"2":{"star_index":1641146,"get_star_ts":1733636783},"1":{"star_index":1639664,"get_star_ts":1733636412}}},"id":411220,"stars":34},"4597883":{"stars":0,"completion_day_level":{},"id":4597883,"local_score":0,"global_score":0,"name":"Rodolfo Moreira","last_star_ts":0},"3881856":{"local_score":0,"global_score":0,"name":"Daniel Aguilar","last_star_ts":0,"completion_day_level":{},"id":3881856,"stars":0},"4670358":{"stars":0,"id":4670358,"completion_day_level":{},"last_star_ts":0,"name":"myName-scor","local_score":0,"global_score":0},"509134":{"stars":0,"completion_day_level":{},"id":509134,"name":"Lin Zhu","local_score":0,"global_score":0,"last_star_ts":0},"3711300":{"local_score":0,"global_score":0,"name":"Kari Vatjus-Anttila","last_star_ts":0,"completion_day_level":{},"id":3711300,"stars":0},"3250972":{"last_star_ts":1733449634,"local_score":811,"name":"Junhee Lee","global_score":0,"id":3250972,"completion_day_level":{"2":{"2":{"star_index":1167906,"get_star_ts":1733410095},"1":{"get_star_ts":1733348253,"star_index":1013627}},"3":{"2":{"get_star_ts":1733449634,"star_index":1258809},"1":{"star_index":1171480,"get_star_ts":1733411365}},"1":{"1":{"star_index":1006808,"get_star_ts":1733346072},"2":{"star_index":1007466,"get_star_ts":1733346292}}},"stars":6},"1192367":{"stars":0,"id":1192367,"completion_day_level":{},"last_star_ts":0,"local_score":0,"global_score":0,"name":"Simon Gurvets"},"218161":{"last_star_ts":0,"name":"Peter Steiwer","local_score":0,"global_score":0,"stars":0,"id":218161,"completion_day_level":{}},"2332597":{"name":"LFY","local_score":0,"global_score":0,"last_star_ts":0,"stars":0,"completion_day_level":{},"id":2332597},"720883":{"global_score":0,"local_score":0,"name":"Aaron Wassall","last_star_ts":0,"completion_day_level":{},"id":720883,"stars":0},"2332378":{"name":"Robert Barbiaux","local_score":0,"global_score":0,"last_star_ts":0,"completion_day_level":{},"id":2332378,"stars":0},"2693297":{"last_star_ts":1734373410,"local_score":2136,"global_score":0,"name":"Sloan Kanaski","stars":15,"id":2693297,"completion_day_level":{"4":{"1":{"star_index":952728,"get_star_ts":1733328468},"2":{"star_index":954682,"get_star_ts":1733329113}},"7":{"2":{"get_star_ts":1734106083,"star_index":2440911},"1":{"star_index":2440691,"get_star_ts":1734105966}},"9":{"1":{"get_star_ts":1734373410,"star_index":2762493}},"2":{"1":{"star_index":694829,"get_star_ts":1733241134},"2":{"get_star_ts":1733241465,"star_index":696098}},"5":{"1":{"get_star_ts":1733415754,"star_index":1183737},"2":{"get_star_ts":1733500551,"star_index":1378413}},"8":{"1":{"star_index":2445022,"get_star_ts":1734108758},"2":{"star_index":2450054,"get_star_ts":1734112308}},"1":{"1":{"star_index":401040,"get_star_ts":1733157640},"2":{"star_index":401798,"get_star_ts":1733157817}},"3":{"2":{"get_star_ts":1733251633,"star_index":732149},"1":{"star_index":729784,"get_star_ts":1733250933}}}},"4293990":{"local_score":1996,"name":null,"global_score":0,"last_star_ts":1734489654,"completion_day_level":{"1":{"2":{"get_star_ts":1733283508,"star_index":806656},"1":{"get_star_ts":1733282566,"star_index":805531}},"3":{"2":{"star_index":835511,"get_star_ts":1733292525},"1":{"get_star_ts":1733290973,"star_index":827854}},"11":{"2":{"get_star_ts":1734425680,"star_index":2812814},"1":{"star_index":2809601,"get_star_ts":1734422857}},"5":{"1":{"star_index":1259925,"get_star_ts":1733450758}},"9":{"1":{"get_star_ts":1734327899,"star_index":2708069}},"4":{"1":{"get_star_ts":1733293720,"star_index":840301},"2":{"star_index":842714,"get_star_ts":1733294388}},"6":{"1":{"get_star_ts":1733465137,"star_index":1286786}},"12":{"1":{"star_index":2877153,"get_star_ts":1734489654}},"2":{"1":{"get_star_ts":1733284895,"star_index":808257},"2":{"get_star_ts":1733289699,"star_index":819603}}},"id":4293990,"stars":14},"523890":{"local_score":0,"global_score":0,"name":"Martin Weber","last_star_ts":0,"stars":0,"completion_day_level":{},"id":523890},"3275803":{"stars":0,"completion_day_level":{},"id":3275803,"local_score":0,"global_score":0,"name":"Luke Schuurman","last_star_ts":0},"1029427":{"id":1029427,"completion_day_level":{},"stars":0,"last_star_ts":0,"local_score":0,"global_score":0,"name":"Nahuel"},"1549867":{"local_score":0,"name":"David Hockenbroch","global_score":0,"last_star_ts":0,"completion_day_level":{},"id":1549867,"stars":0},"17073":{"global_score":0,"local_score":0,"name":"Michael Breen","last_star_ts":0,"stars":0,"completion_day_level":{},"id":17073},"205724":{"stars":0,"id":205724,"completion_day_level":{},"last_star_ts":0,"local_score":0,"name":"a-boertien","global_score":0},"1018992":{"last_star_ts":0,"global_score":0,"local_score":0,"name":"David Pérez Tovar","id":1018992,"completion_day_level":{},"stars":0},"324474":{"stars":0,"completion_day_level":{},"id":324474,"name":"Kevin An","local_score":0,"global_score":0,"last_star_ts":0},"736452":{"stars":0,"completion_day_level":{},"id":736452,"global_score":0,"local_score":0,"name":"FRANCISCO LOPEZ DE LAS HERAS","last_star_ts":0},"697820":{"last_star_ts":0,"local_score":0,"name":"Yaron Munz","global_score":0,"stars":0,"id":697820,"completion_day_level":{}},"292843":{"name":"Tim Leavitt","local_score":0,"global_score":0,"last_star_ts":0,"completion_day_level":{},"id":292843,"stars":0},"1872581":{"last_star_ts":0,"local_score":0,"name":"Davi-Massaru","global_score":0,"id":1872581,"completion_day_level":{},"stars":0},"4432621":{"id":4432621,"completion_day_level":{"16":{"2":{"star_index":2755340,"get_star_ts":1734367287},"1":{"get_star_ts":1734363957,"star_index":2751024}},"5":{"2":{"star_index":1214046,"get_star_ts":1733427468},"1":{"get_star_ts":1733420224,"star_index":1195692}},"12":{"1":{"star_index":2308800,"get_star_ts":1734011662},"2":{"star_index":2366028,"get_star_ts":1734056364}},"9":{"1":{"get_star_ts":1733796094,"star_index":1948764},"2":{"get_star_ts":1733798178,"star_index":1950274}},"13":{"2":{"get_star_ts":1734100172,"star_index":2431513},"1":{"get_star_ts":1734097198,"star_index":2426812}},"14":{"1":{"star_index":2555959,"get_star_ts":1734193834},"2":{"star_index":2561790,"get_star_ts":1734197936}},"15":{"1":{"get_star_ts":1734275872,"star_index":2652844},"2":{"star_index":2660193,"get_star_ts":1734281078}},"11":{"2":{"get_star_ts":1733938027,"star_index":2206947},"1":{"get_star_ts":1733927600,"star_index":2187977}},"8":{"2":{"get_star_ts":1733678681,"star_index":1736975},"1":{"star_index":1734798,"get_star_ts":1733677727}},"17":{"1":{"star_index":2830828,"get_star_ts":1734441899},"2":{"get_star_ts":1734466626,"star_index":2858981}},"2":{"1":{"star_index":357777,"get_star_ts":1733147201},"2":{"star_index":364002,"get_star_ts":1733148737}},"6":{"2":{"get_star_ts":1733492365,"star_index":1356850},"1":{"get_star_ts":1733491190,"star_index":1353983}},"7":{"2":{"get_star_ts":1733601721,"star_index":1588750},"1":{"get_star_ts":1733599814,"star_index":1584985}},"4":{"1":{"star_index":925281,"get_star_ts":1733319715},"2":{"star_index":940394,"get_star_ts":1733324628}},"10":{"2":{"star_index":2090347,"get_star_ts":1733870269},"1":{"get_star_ts":1733869605,"star_index":2089158}},"3":{"2":{"get_star_ts":1733280068,"star_index":802417},"1":{"get_star_ts":1733279584,"star_index":801820}},"1":{"2":{"get_star_ts":1733096656,"star_index":196910},"1":{"get_star_ts":1733093141,"star_index":190037}}},"stars":34,"last_star_ts":1734466626,"name":"abdul-manaan","local_score":4986,"global_score":0},"2574351":{"last_star_ts":0,"local_score":0,"name":"cbarrette9","global_score":0,"stars":0,"id":2574351,"completion_day_level":{}},"1305729":{"id":1305729,"completion_day_level":{},"stars":0,"last_star_ts":0,"local_score":0,"global_score":0,"name":"Алексей Нечаев"},"697042":{"last_star_ts":0,"local_score":0,"name":"logist","global_score":0,"id":697042,"completion_day_level":{},"stars":0}},"owner_id":130669,"day1_ts":1733029200}